odoo10_addon_website_sale_product_unavailable-10.0.1.0.0.99.dev1-py3.8-nspkg.pth
odoo/addons/website_sale_product_unavailable/README.rst
odoo/addons/website_sale_product_unavailable/__init__.py
odoo/addons/website_sale_product_unavailable/__manifest__.py
odoo/addons/website_sale_product_unavailable/controllers/__init__.py
odoo/addons/website_sale_product_unavailable/controllers/main.py
odoo/addons/website_sale_product_unavailable/demo/product_product.xml
odoo/addons/website_sale_product_unavailable/i18n/website_sale_product_unavailable.pot
odoo/addons/website_sale_product_unavailable/models/__init__.py
odoo/addons/website_sale_product_unavailable/models/product_template.py
odoo/addons/website_sale_product_unavailable/static/description/icon.png
odoo/addons/website_sale_product_unavailable/static/src/xml/product_unavailable.xml
odoo/addons/website_sale_product_unavailable/tests/__init__.py
odoo/addons/website_sale_product_unavailable/tests/test_product_template.py
odoo/addons/website_sale_product_unavailable/tests/test_search_order.py
odoo10_addon_website_sale_product_unavailable-10.0.1.0.0.99.dev1.dist-info/METADATA
odoo10_addon_website_sale_product_unavailable-10.0.1.0.0.99.dev1.dist-info/WHEEL
odoo10_addon_website_sale_product_unavailable-10.0.1.0.0.99.dev1.dist-info/namespace_packages.txt
odoo10_addon_website_sale_product_unavailable-10.0.1.0.0.99.dev1.dist-info/top_level.txt
odoo10_addon_website_sale_product_unavailable-10.0.1.0.0.99.dev1.dist-info/RECORD
